yd_addr/__init__.py
yd_addr/frozen.py
yd_addr/resources/addr_dict.json
yd_addr/resources/addr_dict_20210810_1420.json
yd_addr/resources/cutworddict_plus.txt
yd_addr/resources/cutworddict_plus20210803_135830.txt
yd_addr/resources/stopwords3_标点符号.txt
yd_addr/resources/商品品类.txt
yd_addr/src/main/extra_city/address_analysis.py
yd_addr/src/main/extra_city/load_data.py
YundaAddr-1.0.2.dist-info/METADATA
YundaAddr-1.0.2.dist-info/WHEEL
YundaAddr-1.0.2.dist-info/top_level.txt
YundaAddr-1.0.2.dist-info/RECORD
